{"features":[{"geometry":{"coordinates":[104.0597314,30.64319],"type":"Point"},"id":"2696754","properties":{"detail_type":"FACILITY","display":"楼梯","area_id":2696752,"planar_graph":2696743,"location_type":"LOCATION","max_scale":0.01,"data_id":"01J501B0230001","min_scale":50000,"logo":"f38fe10e116c548bc7b1e27db9f53b4d","id":2696754,"category":24097000,"testColor":"#FFFF00"},"type":"Feature"},{"geometry":{"coordinates":[104.0598683,30.6429497],"type":"Point"},"id":"2696757","properties":{"detail_type":"FACILITY","display":"电梯","area_id":2696748,"planar_graph":2696743,"location_type":"LOCATION","max_scale":0.01,"data_id":"01J501B0230004","min_scale":50000,"logo":"f464f429500155596b4bc4927fc62507","id":2696757,"category":24091000,"testColor":"#FFFF00"},"type":"Feature"},{"geometry":{"coordinates":[104.0598431,30.6429633],"type":"Point"},"id":"2696756","properties":{"detail_type":"FACILITY","display":"电梯","area_id":2696746,"planar_graph":2696743,"location_type":"LOCATION","max_scale":0.01,"data_id":"01J501B0230003","min_scale":50000,"logo":"f464f429500155596b4bc4927fc62507","id":2696756,"category":24091000,"testColor":"#FFFF00"},"type":"Feature"},{"geometry":{"coordinates":[104.0598926,30.6429715],"type":"Point"},"id":"2696755","properties":{"detail_type":"FACILITY","display":"电梯","area_id":2696745,"planar_graph":2696743,"location_type":"LOCATION","max_scale":0.01,"data_id":"01J501B0230002","min_scale":50000,"logo":"f464f429500155596b4bc4927fc62507","id":2696755,"category":24091000,"testColor":"#FFFF00"},"type":"Feature"},{"geometry":{"coordinates":[104.0598875,30.642914],"type":"Point"},"id":"2696758","properties":{"detail_type":"FACILITY","display":"楼梯","area_id":2696749,"planar_graph":2696743,"location_type":"LOCATION","max_scale":0.01,"data_id":"01J501B0230005","min_scale":50000,"logo":"f38fe10e116c548bc7b1e27db9f53b4d","id":2696758,"category":24097000,"testColor":"#FFFF00"},"type":"Feature"}],"type":"FeatureCollection"}